omextra/.omlish-manifests.json
omextra/README.md
omextra/__about__.py
omextra/__init__.py
omextra/defs.py
omextra/dynamic.py
omextra/asyncs/__init__.py
omextra/asyncs/all.py
omextra/asyncs/bridge.py
omextra/asyncs/flavors.py
omextra/asyncs/bluelet/LICENSE
omextra/asyncs/bluelet/__init__.py
omextra/asyncs/bluelet/all.py
omextra/asyncs/bluelet/api.py
omextra/asyncs/bluelet/core.py
omextra/asyncs/bluelet/events.py
omextra/asyncs/bluelet/files.py
omextra/asyncs/bluelet/runner.py
omextra/asyncs/bluelet/sockets.py
omextra/formats/__init__.py
omextra/formats/goyaml/LICENSE
omextra/formats/goyaml/__init__.py
omextra/formats/goyaml/ast.py
omextra/formats/goyaml/errors.py
omextra/formats/goyaml/parsing.py
omextra/formats/goyaml/scanning.py
omextra/formats/goyaml/tokens.py
omextra/formats/json/Json.g4
omextra/formats/json/__init__.py
omextra/formats/json/_antlr/JsonLexer.py
omextra/formats/json/_antlr/JsonListener.py
omextra/formats/json/_antlr/JsonParser.py
omextra/formats/json/_antlr/JsonVisitor.py
omextra/formats/json/_antlr/__init__.py
omextra/formats/json5/Json5.g4
omextra/formats/json5/__init__.py
omextra/formats/json5/parsing.py
omextra/formats/json5/_antlr/Json5Lexer.py
omextra/formats/json5/_antlr/Json5Listener.py
omextra/formats/json5/_antlr/Json5Parser.py
omextra/formats/json5/_antlr/Json5Visitor.py
omextra/formats/json5/_antlr/__init__.py
omextra/io/__init__.py
omextra/io/trampoline.py
omextra/specs/__init__.py
omextra/specs/proto/Protobuf3.g4
omextra/specs/proto/__init__.py
omextra/specs/proto/nodes.py
omextra/specs/proto/parsing.py
omextra/specs/proto/_antlr/Protobuf3Lexer.py
omextra/specs/proto/_antlr/Protobuf3Listener.py
omextra/specs/proto/_antlr/Protobuf3Parser.py
omextra/specs/proto/_antlr/Protobuf3Visitor.py
omextra/specs/proto/_antlr/__init__.py
omextra/sql/__init__.py
omextra/sql/alchemy/__init__.py
omextra/sql/alchemy/asyncs.py
omextra/sql/parsing/Minisql.g4
omextra/sql/parsing/__init__.py
omextra/sql/parsing/parsing.py
omextra-0.0.0.dev516.dist-info/licenses/LICENSE
omextra-0.0.0.dev516.dist-info/METADATA
omextra-0.0.0.dev516.dist-info/WHEEL
omextra-0.0.0.dev516.dist-info/entry_points.txt
omextra-0.0.0.dev516.dist-info/top_level.txt
omextra-0.0.0.dev516.dist-info/RECORD
